<?xml version="1.0" encoding="utf-8"?>
<Document>
  <Engineering version="V21" />
  <SW.Blocks.GlobalDB ID="0">
    <AttributeList>
      <Interface>
        <Sections xmlns="http://www.siemens.com/automation/Openness/SW/Interface/v5">
          <Section Name="Static">
            <Member Name="V" Datatype="Array[0..&quot;K_NumValvolaFestoVTEM&quot;] of &quot;Std_ValvoleVTEM&quot;" Remanence="Retain">
              <Sections>
                <Section Name="None">
                  <Member Name="Input" Datatype="Struct">
                    <Member Name="wBusDataFromVTEM0" Datatype="Word">
                      <Subelement Path="0">
                        <StartValue>16#0000</StartValue>
                      </Subelement>
                    </Member>
                    <Member Name="wBusDataFromVTEM1" Datatype="Word">
                      <Subelement Path="0">
                        <StartValue>16#0000</StartValue>
                      </Subelement>
                    </Member>
                    <Member Name="wBusDataFromVTEM2" Datatype="Word">
                      <Subelement Path="0">
                        <StartValue>16#0000</StartValue>
                      </Subelement>
                    </Member>
                    <Member Name="xEnable" Datatype="Bool">
                      <Subelement Path="0">
                        <StartValue>FALSE</StartValue>
                      </Subelement>
                    </Member>
                    <Member Name="bySetValveMode" Datatype="Byte">
                      <Subelement Path="0">
                        <StartValue>16#00</StartValue>
                      </Subelement>
                    </Member>
                    <Member Name="bySetAppControl" Datatype="Byte">
                      <Subelement Path="0">
                        <StartValue>16#00</StartValue>
                      </Subelement>
                    </Member>
                    <Member Name="bySetAppOption" Datatype="Byte">
                      <Subelement Path="0">
                        <StartValue>16#00</StartValue>
                      </Subelement>
                    </Member>
                    <Member Name="iSetpointValue1" Datatype="Int">
                      <Subelement Path="0">
                        <StartValue>0</StartValue>
                      </Subelement>
                    </Member>
                    <Member Name="iSetpointValue2" Datatype="Int">
                      <Subelement Path="0">
                        <StartValue>0</StartValue>
                      </Subelement>
                    </Member>
                    <Member Name="xManualAcknowledge" Datatype="Bool">
                      <Subelement Path="0">
                        <StartValue>FALSE</StartValue>
                      </Subelement>
                    </Member>
                  </Member>
                  <Member Name="Output" Datatype="Struct">
                    <Member Name="byActualValveMode" Datatype="Byte">
                      <Subelement Path="0">
                        <StartValue>16#00</StartValue>
                      </Subelement>
                    </Member>
                    <Member Name="byActualValveState" Datatype="Byte">
                      <Subelement Path="0">
                        <StartValue>16#00</StartValue>
                      </Subelement>
                    </Member>
                    <Member Name="byActualAppState" Datatype="Byte">
                      <Subelement Path="0">
                        <StartValue>16#00</StartValue>
                      </Subelement>
                    </Member>
                    <Member Name="iActualValue1" Datatype="Int">
                      <Subelement Path="0">
                        <StartValue>0</StartValue>
                      </Subelement>
                    </Member>
                    <Member Name="iActualValue2" Datatype="Int">
                      <Subelement Path="0">
                        <StartValue>0</StartValue>
                      </Subelement>
                    </Member>
                    <Member Name="iResponseToValveModeSet" Datatype="Int">
                      <Subelement Path="0">
                        <StartValue>0</StartValue>
                      </Subelement>
                    </Member>
                    <Member Name="sResponseToValveModeSet" Datatype="String">
                      <Subelement Path="0">
                        <StartValue>''</StartValue>
                      </Subelement>
                    </Member>
                    <Member Name="iErrorCode" Datatype="Int">
                      <Subelement Path="0">
                        <StartValue>0</StartValue>
                      </Subelement>
                    </Member>
                  </Member>
                  <Member Name="InOut" Datatype="Struct">
                    <Member Name="wBusDataToVTEM0" Datatype="Word">
                      <Subelement Path="0">
                        <StartValue>16#0000</StartValue>
                      </Subelement>
                    </Member>
                    <Member Name="wBusDataToVTEM1" Datatype="Word">
                      <Subelement Path="0">
                        <StartValue>16#0000</StartValue>
                      </Subelement>
                    </Member>
                    <Member Name="wBusDataToVTEM2" Datatype="Word">
                      <Subelement Path="0">
                        <StartValue>16#0000</StartValue>
                      </Subelement>
                    </Member>
                  </Member>
                  <Member Name="Static" Datatype="Struct">
                    <Member Name="aw_OperationCommand" Datatype="Array[0..2] of Word">
                      <Subelement Path="0,0">
                        <StartValue>16#0000</StartValue>
                      </Subelement>
                      <Subelement Path="0,1">
                        <StartValue>16#0000</StartValue>
                      </Subelement>
                      <Subelement Path="0,2">
                        <StartValue>16#0000</StartValue>
                      </Subelement>
                    </Member>
                    <Member Name="iCommandNumber" Datatype="Int">
                      <Subelement Path="0">
                        <StartValue>0</StartValue>
                      </Subelement>
                    </Member>
                    <Member Name="iInvalidCommand" Datatype="Int">
                      <Subelement Path="0">
                        <StartValue>0</StartValue>
                      </Subelement>
                    </Member>
                    <Member Name="iRecChannel" Datatype="Int">
                      <Subelement Path="0">
                        <StartValue>0</StartValue>
                      </Subelement>
                    </Member>
                    <Member Name="iRecTransferCtrl" Datatype="Int">
                      <Subelement Path="0">
                        <StartValue>0</StartValue>
                      </Subelement>
                    </Member>
                    <Member Name="iRecAddressedTargetType" Datatype="Int">
                      <Subelement Path="0">
                        <StartValue>0</StartValue>
                      </Subelement>
                    </Member>
                    <Member Name="iRecIndex" Datatype="Int">
                      <Subelement Path="0">
                        <StartValue>0</StartValue>
                      </Subelement>
                    </Member>
                    <Member Name="iRecTransferValue" Datatype="Int">
                      <Subelement Path="0">
                        <StartValue>0</StartValue>
                      </Subelement>
                    </Member>
                    <Member Name="iActualValveMode" Datatype="Int">
                      <Subelement Path="0">
                        <StartValue>0</StartValue>
                      </Subelement>
                    </Member>
                    <Member Name="iValveState" Datatype="Int">
                      <Subelement Path="0">
                        <StartValue>0</StartValue>
                      </Subelement>
                    </Member>
                    <Member Name="xInvalidInput" Datatype="Bool">
                      <Subelement Path="0">
                        <StartValue>FALSE</StartValue>
                      </Subelement>
                    </Member>
                    <Member Name="xLastManualAcknowledge" Datatype="Bool">
                      <Subelement Path="0">
                        <StartValue>FALSE</StartValue>
                      </Subelement>
                    </Member>
                    <Member Name="xAcknowledging_in_progress" Datatype="Bool">
                      <Subelement Path="0">
                        <StartValue>FALSE</StartValue>
                      </Subelement>
                    </Member>
                    <Member Name="xMalfunctionReading_Done" Datatype="Bool">
                      <Subelement Path="0">
                        <StartValue>FALSE</StartValue>
                      </Subelement>
                    </Member>
                    <Member Name="iMalfunctionListEntry" Datatype="Int">
                      <Subelement Path="0">
                        <StartValue>0</StartValue>
                      </Subelement>
                    </Member>
                    <Member Name="iRecMalfunctionCode" Datatype="Int">
                      <Subelement Path="0">
                        <StartValue>0</StartValue>
                      </Subelement>
                    </Member>
                    <Member Name="iRecMalfunctionRating" Datatype="Int">
                      <Subelement Path="0">
                        <StartValue>0</StartValue>
                      </Subelement>
                    </Member>
                    <Member Name="iActualAppState" Datatype="Int">
                      <Subelement Path="0">
                        <StartValue>0</StartValue>
                      </Subelement>
                    </Member>
                    <Member Name="eResponseToValveModeSet" Datatype="&quot;Std_eResponseToValveModeSet&quot;">
                      <Sections>
                        <Section Name="None">
                          <Member Name="reserved" Datatype="Int">
                            <Subelement Path="0">
                              <StartValue>0</StartValue>
                            </Subelement>
                          </Member>
                          <Member Name="invalid_SetValveMode" Datatype="Int">
                            <Subelement Path="0">
                              <StartValue>1</StartValue>
                            </Subelement>
                          </Member>
                          <Member Name="invalid_SetAppControl" Datatype="Int">
                            <Subelement Path="0">
                              <StartValue>2</StartValue>
                            </Subelement>
                          </Member>
                          <Member Name="invalid_SetAppOption" Datatype="Int">
                            <Subelement Path="0">
                              <StartValue>3</StartValue>
                            </Subelement>
                          </Member>
                          <Member Name="invalid_SetPointValue1" Datatype="Int">
                            <Subelement Path="0">
                              <StartValue>4</StartValue>
                            </Subelement>
                          </Member>
                          <Member Name="invalid_SetPointValue2" Datatype="Int">
                            <Subelement Path="0">
                              <StartValue>5</StartValue>
                            </Subelement>
                          </Member>
                          <Member Name="invalid_configuration" Datatype="Int">
                            <Subelement Path="0">
                              <StartValue>6</StartValue>
                            </Subelement>
                          </Member>
                          <Member Name="access_denied_WebConfig" Datatype="Int">
                            <Subelement Path="0">
                              <StartValue>10</StartValue>
                            </Subelement>
                          </Member>
                          <Member Name="access_denied_saving_parametrisation" Datatype="Int">
                            <Subelement Path="0">
                              <StartValue>11</StartValue>
                            </Subelement>
                          </Member>
                          <Member Name="no_license_for_this_MA" Datatype="Int">
                            <Subelement Path="0">
                              <StartValue>12</StartValue>
                            </Subelement>
                          </Member>
                          <Member Name="all_licenses_in_use" Datatype="Int">
                            <Subelement Path="0">
                              <StartValue>13</StartValue>
                            </Subelement>
                          </Member>
                          <Member Name="invalid_license_file" Datatype="Int">
                            <Subelement Path="0">
                              <StartValue>14</StartValue>
                            </Subelement>
                          </Member>
                          <Member Name="no_valve_detected" Datatype="Int">
                            <Subelement Path="0">
                              <StartValue>15</StartValue>
                            </Subelement>
                          </Member>
                          <Member Name="valve_self_calibration_running" Datatype="Int">
                            <Subelement Path="0">
                              <StartValue>16</StartValue>
                            </Subelement>
                          </Member>
                          <Member Name="no_TransferMode_with_this_FB" Datatype="Int">
                            <Subelement Path="0">
                              <StartValue>1020</StartValue>
                            </Subelement>
                          </Member>
                          <Member Name="preparing_for_start" Datatype="Int">
                            <Subelement Path="0">
                              <StartValue>1031</StartValue>
                            </Subelement>
                          </Member>
                          <Member Name="starting" Datatype="Int">
                            <Subelement Path="0">
                              <StartValue>1032</StartValue>
                            </Subelement>
                          </Member>
                          <Member Name="MA_running" Datatype="Int">
                            <Subelement Path="0">
                              <StartValue>1033</StartValue>
                            </Subelement>
                          </Member>
                          <Member Name="Transfermode_running" Datatype="Int">
                            <Subelement Path="0">
                              <StartValue>1034</StartValue>
                            </Subelement>
                          </Member>
                          <Member Name="stopping" Datatype="Int">
                            <Subelement Path="0">
                              <StartValue>1035</StartValue>
                            </Subelement>
                          </Member>
                          <Member Name="all_MAs_stopped" Datatype="Int">
                            <Subelement Path="0">
                              <StartValue>1036</StartValue>
                            </Subelement>
                          </Member>
                          <Member Name="acknowledge_needed" Datatype="Int">
                            <Subelement Path="0">
                              <StartValue>1037</StartValue>
                            </Subelement>
                          </Member>
                          <Member Name="failure" Datatype="Int">
                            <Subelement Path="0">
                              <StartValue>1038</StartValue>
                            </Subelement>
                          </Member>
                          <Member Name="preparing_for_acknowledge" Datatype="Int">
                            <Subelement Path="0">
                              <StartValue>1040</StartValue>
                            </Subelement>
                          </Member>
                          <Member Name="acknowledging" Datatype="Int">
                            <Subelement Path="0">
                              <StartValue>1041</StartValue>
                            </Subelement>
                          </Member>
                          <Member Name="all_errors_acknowledged" Datatype="Int">
                            <Subelement Path="0">
                              <StartValue>1042</StartValue>
                            </Subelement>
                          </Member>
                          <Member Name="failure_still_active" Datatype="Int">
                            <Subelement Path="0">
                              <StartValue>1043</StartValue>
                            </Subelement>
                          </Member>
                          <Member Name="no_Communication" Datatype="Int">
                            <Subelement Path="0">
                              <StartValue>1050</StartValue>
                            </Subelement>
                          </Member>
                          <Member Name="FB_not_enabled" Datatype="Int">
                            <Subelement Path="0">
                              <StartValue>1051</StartValue>
                            </Subelement>
                          </Member>
                        </Section>
                      </Sections>
                    </Member>
                    <Member Name="eValveState" Datatype="&quot;Std_eValveState&quot;">
                      <Sections>
                        <Section Name="None">
                          <Member Name="NotReady" Datatype="Int">
                            <Subelement Path="0">
                              <StartValue>0</StartValue>
                            </Subelement>
                          </Member>
                          <Member Name="Configurable" Datatype="Int">
                            <Subelement Path="0">
                              <StartValue>1</StartValue>
                            </Subelement>
                          </Member>
                          <Member Name="Running" Datatype="Int">
                            <Subelement Path="0">
                              <StartValue>2</StartValue>
                            </Subelement>
                          </Member>
                          <Member Name="Failure" Datatype="Int">
                            <Subelement Path="0">
                              <StartValue>3</StartValue>
                            </Subelement>
                          </Member>
                        </Section>
                      </Sections>
                    </Member>
                  </Member>
                </Section>
              </Sections>
            </Member>
          </Section>
        </Sections>
      </Interface>
      <MemoryLayout>Optimized</MemoryLayout>
      <MemoryReserve>100</MemoryReserve>
      <Name>ValvolaFesto_VTEM</Name>
      <Namespace />
      <Number>15</Number>
      <ProgrammingLanguage>DB</ProgrammingLanguage>
    </AttributeList>
    <ObjectList>
      <MultilingualText ID="1" CompositionName="Comment">
        <ObjectList>
          <MultilingualTextItem ID="2" CompositionName="Items">
            <AttributeList>
              <Culture>de-DE</Culture>
              <Text />
            </AttributeList>
          </MultilingualTextItem>
          <MultilingualTextItem ID="3" CompositionName="Items">
            <AttributeList>
              <Culture>en-GB</Culture>
              <Text />
            </AttributeList>
          </MultilingualTextItem>
          <MultilingualTextItem ID="4" CompositionName="Items">
            <AttributeList>
              <Culture>es-ES</Culture>
              <Text />
            </AttributeList>
          </MultilingualTextItem>
          <MultilingualTextItem ID="5" CompositionName="Items">
            <AttributeList>
              <Culture>fr-FR</Culture>
              <Text />
            </AttributeList>
          </MultilingualTextItem>
          <MultilingualTextItem ID="6" CompositionName="Items">
            <AttributeList>
              <Culture>it-IT</Culture>
              <Text />
            </AttributeList>
          </MultilingualTextItem>
        </ObjectList>
      </MultilingualText>
      <MultilingualText ID="7" CompositionName="Title">
        <ObjectList>
          <MultilingualTextItem ID="8" CompositionName="Items">
            <AttributeList>
              <Culture>de-DE</Culture>
              <Text />
            </AttributeList>
          </MultilingualTextItem>
          <MultilingualTextItem ID="9" CompositionName="Items">
            <AttributeList>
              <Culture>en-GB</Culture>
              <Text />
            </AttributeList>
          </MultilingualTextItem>
          <MultilingualTextItem ID="A" CompositionName="Items">
            <AttributeList>
              <Culture>es-ES</Culture>
              <Text />
            </AttributeList>
          </MultilingualTextItem>
          <MultilingualTextItem ID="B" CompositionName="Items">
            <AttributeList>
              <Culture>fr-FR</Culture>
              <Text />
            </AttributeList>
          </MultilingualTextItem>
          <MultilingualTextItem ID="C" CompositionName="Items">
            <AttributeList>
              <Culture>it-IT</Culture>
              <Text />
            </AttributeList>
          </MultilingualTextItem>
        </ObjectList>
      </MultilingualText>
    </ObjectList>
  </SW.Blocks.GlobalDB>
</Document>